pysubs2/__init__.py
pysubs2/__main__.py
pysubs2/cli.py
pysubs2/common.py
pysubs2/exceptions.py
pysubs2/ssaevent.py
pysubs2/ssafile.py
pysubs2/ssastyle.py
pysubs2/time.py
pysubs2-1.7.0.dist-info/LICENSE.txt
pysubs2-1.7.0.dist-info/METADATA
pysubs2-1.7.0.dist-info/WHEEL
pysubs2-1.7.0.dist-info/entry_points.txt
pysubs2-1.7.0.dist-info/top_level.txt
pysubs2-1.7.0.dist-info/RECORD
