Metadata-Version: 2.1
Name: pysubs2
Version: 1.7.0
Summary: A library for editing subtitle files
Home-page: https://github.com/tkarabela/pysubs2
Author: Tomas Karabela
Author-email: tkarabela@seznam.cz
License: MIT
Project-URL: Documentation, https://pysubs2.readthedocs.io
Project-URL: Bug Tracker, https://github.com/tkarabela/pysubs2/issues
Keywords: SubStation,SubRip,MicroDVD,MPL2,WebVTT,ass,srt,sub,vtt,subtitles,captions
Classifier: Programming Language :: Python
Classifier: Programming Language :: Python :: 3
Classifier: Programming Language :: Python :: 3.8
Classifier: Programming Language :: Python :: 3.9
Classifier: Programming Language :: Python :: 3.10
Classifier: Programming Language :: Python :: 3.11
Classifier: Programming Language :: Python :: 3.12
Classifier: Development Status :: 5 - Production/Stable
Classifier: Topic :: Software Development :: Libraries :: Python Modules
Classifier: Topic :: Text Processing :: Markup
Classifier: Topic :: Multimedia :: Video
Classifier: Intended Audience :: Developers
Classifier: Intended Audience :: End Users/Desktop
Classifier: Operating System :: OS Independent
Classifier: License :: OSI Approved :: MIT License
Classifier: Typing :: Typed
Requires-Python: >=3.8
License-File: LICENSE.txt
